sd_prompt_reader/.DS_Store
sd_prompt_reader/__init__.py
sd_prompt_reader/__version__.py
sd_prompt_reader/app.py
sd_prompt_reader/button.py
sd_prompt_reader/cli.py
sd_prompt_reader/constants.py
sd_prompt_reader/ctkdnd.py
sd_prompt_reader/format/.DS_Store
sd_prompt_reader/format/__init__.py
sd_prompt_reader/format/a1111.py
sd_prompt_reader/format/base_format.py
sd_prompt_reader/format/comfyui.py
sd_prompt_reader/format/drawthings.py
sd_prompt_reader/format/easydiffusion.py
sd_prompt_reader/format/fooocus.py
sd_prompt_reader/format/invokeai.py
sd_prompt_reader/format/novelai.py
sd_prompt_reader/format/swarmui.py
sd_prompt_reader/image_data_reader.py
sd_prompt_reader/logger.py
sd_prompt_reader/parameter_viewer.py
sd_prompt_reader/prompt_viewer.py
sd_prompt_reader/resources/.DS_Store
sd_prompt_reader/resources/__init__.py
sd_prompt_reader/resources/check_circle_24.png
sd_prompt_reader/resources/check_circle_24_alpha.png
sd_prompt_reader/resources/cleaning_services_24.png
sd_prompt_reader/resources/cleaning_services_24_alpha.png
sd_prompt_reader/resources/content_copy_20.png
sd_prompt_reader/resources/content_copy_20_alpha.png
sd_prompt_reader/resources/content_copy_24.png
sd_prompt_reader/resources/content_copy_24_alpha.png
sd_prompt_reader/resources/description_24.png
sd_prompt_reader/resources/description_24_alpha.png
sd_prompt_reader/resources/edit_24.png
sd_prompt_reader/resources/edit_24_alpha.png
sd_prompt_reader/resources/edit_off_24.png
sd_prompt_reader/resources/edit_off_24_alpha.png
sd_prompt_reader/resources/error_24.png
sd_prompt_reader/resources/error_24_alpha.png
sd_prompt_reader/resources/expand_more_24.png
sd_prompt_reader/resources/expand_more_24_alpha.png
sd_prompt_reader/resources/gray.json
sd_prompt_reader/resources/icon-cli.ico
sd_prompt_reader/resources/icon-cube.png
sd_prompt_reader/resources/icon-gui.ico
sd_prompt_reader/resources/icon.icns
sd_prompt_reader/resources/icon.png
sd_prompt_reader/resources/info_24.png
sd_prompt_reader-1.3.5.dist-info/LICENSE
sd_prompt_reader-1.3.5.dist-info/METADATA
sd_prompt_reader-1.3.5.dist-info/WHEEL
sd_prompt_reader-1.3.5.dist-info/entry_points.txt
sd_prompt_reader-1.3.5.dist-info/RECORD
