Metadata-Version: 2.1
Name: sd-prompt-reader
Version: 1.3.5
Summary: A simple standalone viewer for reading prompt from Stable Diffusion generated image outside the webui.
Home-page: https://github.com/receyuki/stable-diffusion-prompt-reader
License: MIT
Author: receyuki
Author-email: receyuki@gmail.com
Requires-Python: >=3.10,<4.0
Classifier: License :: OSI Approved :: MIT License
Classifier: Operating System :: OS Independent
Classifier: Programming Language :: Python :: 3
Classifier: Programming Language :: Python :: 3.10
Classifier: Programming Language :: Python :: 3.11
Classifier: Programming Language :: Python :: 3.12
Requires-Dist: click (>=8.1.7,<8.2.0)
Requires-Dist: ctktooltip (>=0.8,<1.0)
Requires-Dist: customtkinter (>=5.2.2,<5.3.0)
Requires-Dist: pefile (>=2023.2.7,<2023.3.0)
Requires-Dist: piexif (>=1.1.3,<1.2.0)
Requires-Dist: pillow (==10.3.0)
Requires-Dist: pyobjc-framework-cocoa (==10.2) ; sys_platform == "darwin"
Requires-Dist: pyobjus (>=1.2.3,<1.3.0) ; sys_platform == "darwin"
Requires-Dist: pyperclip (>=1.8.2,<1.9.0)
Requires-Dist: requests (>=2.32.1,<2.33.0)
Requires-Dist: tkinterdnd2-universal (>=1.7.3,<1.8.0)
Requires-Dist: toml (>=0.10.2,<0.11.0)
Project-URL: Bug Tracker, https://github.com/receyuki/stable-diffusion-prompt-reader/issues
Project-URL: Documentation, https://github.com/receyuki/stable-diffusion-prompt-reader
Project-URL: Repository, https://github.com/receyuki/stable-diffusion-prompt-reader
